xsd_to_django_model/__init__.py
xsd_to_django_model/xsd_to_django_model.py
xsd_to_django_model-0.8.9.data/scripts/xsd_to_django_model.py
xsd_to_django_model-0.8.9.dist-info/DESCRIPTION.rst
xsd_to_django_model-0.8.9.dist-info/METADATA
xsd_to_django_model-0.8.9.dist-info/RECORD
xsd_to_django_model-0.8.9.dist-info/WHEEL
xsd_to_django_model-0.8.9.dist-info/metadata.json
xsd_to_django_model-0.8.9.dist-info/top_level.txt
