Metadata-Version: 2.0
Name: xsd-to-django-model
Version: 0.8.9
Summary: Generate Django models from an XSD schema description (and a bunch of hints)
Home-page: http://github.com/tuffnatty/xsd_to_django_model
Author: Phil Krylov
Author-email: phil.krylov@gmail.com
License: GNU General Public License v3 (GPLv3)
Platform: any
Classifier: Programming Language :: Python
Classifier: Development Status :: 4 - Beta
Classifier: Natural Language :: English
Classifier: Environment :: Console
Classifier: Intended Audience :: Developers
Classifier: Framework :: Django
Classifier: License :: OSI Approved :: GNU General Public License v3 (GPLv3)
Classifier: Operating System :: OS Independent
Classifier: Topic :: Database
Classifier: Topic :: Software Development :: Code Generators
Classifier: Topic :: Software Development :: Libraries :: Python Modules
Classifier: Topic :: Text Processing :: Markup :: XML
Requires-Dist: docopt
Requires-Dist: lxml
